yaqd_mcc/VERSION
yaqd_mcc/__init__.py
yaqd_mcc/__version__.py
yaqd_mcc/_mcc_118.py
yaqd_mcc/_mcc_152_aout.py
yaqd_mcc/_mcc_ulw_sensor.py
yaqd_mcc/mcc-118.avpr
yaqd_mcc/mcc-118.toml
yaqd_mcc/mcc-152-aout.avpr
yaqd_mcc/mcc-152-aout.toml
yaqd_mcc/mcc-ulw-sensor.avpr
yaqd_mcc/mcc-ulw-sensor.toml
yaqd_mcc-2023.8.0.dist-info/entry_points.txt
yaqd_mcc-2023.8.0.dist-info/LICENSE
yaqd_mcc-2023.8.0.dist-info/WHEEL
yaqd_mcc-2023.8.0.dist-info/METADATA
yaqd_mcc-2023.8.0.dist-info/RECORD
